odoo/addons/shopinvader_schema_sale_state/README.rst
odoo/addons/shopinvader_schema_sale_state/__init__.py
odoo/addons/shopinvader_schema_sale_state/__manifest__.py
odoo/addons/shopinvader_schema_sale_state/i18n/shopinvader_schema_sale_state.pot
odoo/addons/shopinvader_schema_sale_state/readme/CONTRIBUTORS.rst
odoo/addons/shopinvader_schema_sale_state/readme/DESCRIPTION.rst
odoo/addons/shopinvader_schema_sale_state/schemas/__init__.py
odoo/addons/shopinvader_schema_sale_state/schemas/sale.py
odoo/addons/shopinvader_schema_sale_state/static/description/index.html
odoo/addons/shopinvader_schema_sale_state/tests/__init__.py
odoo/addons/shopinvader_schema_sale_state/tests/test_sale_schema.py
odoo_addon_shopinvader_schema_sale_state-16.0.1.0.1.dist-info/METADATA
odoo_addon_shopinvader_schema_sale_state-16.0.1.0.1.dist-info/WHEEL
odoo_addon_shopinvader_schema_sale_state-16.0.1.0.1.dist-info/top_level.txt
odoo_addon_shopinvader_schema_sale_state-16.0.1.0.1.dist-info/RECORD
